neuralfoil/__init__.py
neuralfoil/_basic_data_type.py
neuralfoil/main.py
neuralfoil/nn_weights_and_biases/nn-large.npz
neuralfoil/nn_weights_and_biases/nn-medium.npz
neuralfoil/nn_weights_and_biases/nn-small.npz
neuralfoil/nn_weights_and_biases/nn-xlarge.npz
neuralfoil/nn_weights_and_biases/nn-xsmall.npz
neuralfoil/nn_weights_and_biases/nn-xxlarge.npz
neuralfoil/nn_weights_and_biases/nn-xxsmall.npz
neuralfoil/nn_weights_and_biases/nn-xxxlarge.npz
neuralfoil/nn_weights_and_biases/scaled_input_distribution.npz
neuralfoil_torch-0.3.2.dist-info/licenses/LICENSE.txt
neuralfoil_torch-0.3.2.dist-info/METADATA
neuralfoil_torch-0.3.2.dist-info/WHEEL
neuralfoil_torch-0.3.2.dist-info/top_level.txt
neuralfoil_torch-0.3.2.dist-info/RECORD
