Metadata-Version: 2.4
Name: neuralFoil-torch
Version: 0.3.2
Summary: NeuralFoil-torch a fork of Neuralfoil that uses torch instead of numpy for faster neural net predictions.
Home-page: https://github.com/DavidRamosArchilla/NeuralFoil-torch
Author: David Ramos, Peter Sharpe
Project-URL: Source, https://github.com/DavidRamosArchilla/NeuralFoil-torch
Project-URL: Bug Reports, https://github.com/DavidRamosArchilla/NeuralFoil-torch/issues
Keywords: python machine learning analysis optimization aerospace airplane cfd aircraft hydrodynamics aerodynamics sailing propeller airfoil xfoil design mdo mdao physics informed neural network
Classifier: Development Status :: 5 - Production/Stable
Classifier: Intended Audience :: Science/Research
Classifier: Topic :: Scientific/Engineering :: Physics
Classifier: License :: OSI Approved :: MIT License
Classifier: Programming Language :: Python :: 3
Requires-Python: >=3.9
License-File: LICENSE.txt
Requires-Dist: numpy>=1
Requires-Dist: torch
Requires-Dist: aerosandbox<4.3.0,>=4.2.4
Provides-Extra: training
Requires-Dist: torch; extra == "training"
Requires-Dist: ray; extra == "training"
Requires-Dist: polars; extra == "training"
Requires-Dist: tqdm; extra == "training"
Provides-Extra: test
Requires-Dist: pytest; extra == "test"
Requires-Dist: nbval; extra == "test"
Provides-Extra: docs
Requires-Dist: sphinx; extra == "docs"
Requires-Dist: furo; extra == "docs"
Requires-Dist: sphinx-autoapi; extra == "docs"
Dynamic: author
Dynamic: classifier
Dynamic: description
Dynamic: description-content-type
Dynamic: home-page
Dynamic: keywords
Dynamic: license-file
Dynamic: project-url
Dynamic: provides-extra
Dynamic: requires-dist
Dynamic: requires-python
Dynamic: summary
